README.md
impfuzzy_util.c
pyimpfuzzy.py
setup.py
pyimpfuzzy.egg-info/PKG-INFO
pyimpfuzzy.egg-info/SOURCES.txt
pyimpfuzzy.egg-info/dependency_links.txt
pyimpfuzzy.egg-info/requires.txt
pyimpfuzzy.egg-info/top_level.txt