Metadata-Version: 2.1
Name: pyimpfuzzy
Version: 0.5
Summary: Python modules for impfuzzy
Home-page: https://github.com/JPCERTCC/impfuzzy/
Author: JPCERT/CC Analysis Center
Author-email: aa-info@jpcert.or.jp
License: the GNU General Public License version 2
Platform: UNKNOWN
